metapop/__init__.py
metapop/metapop_codon_bias.py
metapop/metapop_filter.py
metapop/metapop_fst.py
metapop/metapop_helper_functions.py
metapop/metapop_main.py
metapop/metapop_mine_reads.py
metapop/metapop_snp_call.py
metapop/metapop_r/MetaPop_Codon_Bias_Calc.R
metapop/metapop_r/MetaPop_Codon_Bias_Calc_Independent.R
metapop/metapop_r/MetaPop_Codon_Bias_Viz.R
metapop/metapop_r/MetaPop_Fisher_Exact.R
metapop/metapop_r/MetaPop_Macrodiversity.R
metapop/metapop_r/MetaPop_Microdiversity.R
metapop/metapop_r/MetaPop_Microdiversity_Visualizations.R
metapop/metapop_r/MetaPop_Preprocessing_Summaries.R
metapop-0.0.60.dist-info/METADATA
metapop-0.0.60.dist-info/WHEEL
metapop-0.0.60.dist-info/entry_points.txt
metapop-0.0.60.dist-info/top_level.txt
metapop-0.0.60.dist-info/RECORD
