Metadata-Version: 2.1
Name: metapop
Version: 0.0.60
Summary: A metagenomic sta		tistic pipeline.
Home-page: UNKNOWN
Author: Kenji Gerhardt
Author-email: kenji.gerhardt@gmail.com
License: UNKNOWN
Platform: UNKNOWN
Requires-Python: >=3
